fft.v
module fft(CLK, RST_N, write, start, in0_real , in0_imag, in1_real, in1_imag, 
 in2_real  ,in2_imag, in3_real  ,in3_imag, in4_real  ,in4_imag, in5_real  ,in5_imag,
 in6_real  ,in6_imag, in7_real  ,in7_imag, ready, out0_real ,out0_imag, out1_real, 
 out1_imag, out2_real ,out2_imag, out3_real ,out3_imag, out4_real ,out4_imag, 
 out5_real ,out5_imag, out6_real ,out6_imag, out7_real ,out7_imag);

  input CLK, RST_N;
  input write, start;
  input wire signed [15:0]  in0_real  ,in0_imag;
  input wire signed [15:0]  in1_real  ,in1_imag;
  input wire signed [15:0]  in2_real  ,in2_imag;
  input wire signed [15:0]  in3_real  ,in3_imag;
  input wire signed [15:0]  in4_real  ,in4_imag;
  input wire signed [15:0]  in5_real  ,in5_imag;
  input wire signed [15:0]  in6_real  ,in6_imag;
  input wire signed [15:0]  in7_real  ,in7_imag;
  output reg ready;
  output wire signed [15:0] out0_real ,out0_imag;
  output wire signed [15:0] out1_real ,out1_imag;
  output wire signed [15:0] out2_real ,out2_imag;
  output wire signed [15:0] out3_real ,out3_imag;
  output wire signed [15:0] out4_real ,out4_imag;
  output wire signed [15:0] out5_real ,out5_imag;
  output wire signed [15:0] out6_real ,out6_imag;
  output wire signed [15:0] out7_real ,out7_imag;

  reg signed [15:0] i0_real, i0_imag;
  reg signed [15:0] i1_real, i1_imag;
  reg signed [15:0] i2_real, i2_imag;
  reg signed [15:0] i3_real, i3_imag;
  reg signed [15:0] i4_real, i4_imag;
  reg signed [15:0] i5_real, i5_imag;
  reg signed [15:0] i6_real, i6_imag;
  reg signed [15:0] i7_real, i7_imag;
  reg [2:0] stage;

  reg signed [15:0] g_real [0:7];   // Declare g_real as an array of registers to store real part of stage 1 results
  reg signed [15:0] g_imag [0:7];   // Declare g_imag as an array of registers to store imag part of stage 1 results
  reg signed [15:0] h_real [0:7];   // Declare h_real as an array of registers to store real part of stage 2 results
  reg signed [15:0] h_imag [0:7];   // Declare h_imag as an array of registers to store imag part of stage 2 results
  reg signed [15:0] i_real [0:7];   // Declare i_real as an array of registers to store real part of stage 3 results
  reg signed [15:0] i_imag [0:7];   // Declare i_imag as an array of registers to store imag part of stage 3 results

  reg signed [15:0] temp1,temp2,temp3,temp0;
  reg signed [31:0] h5_prime_real;  // 32 bit register to store real part of h[5] * (W8 ^ 1)
  reg signed [31:0] h5_prime_imag;  // 32 bit register to store imag part of h[5] * (W8 ^ 1)
  reg signed [31:0] h7_prime_real;  // 32 bit register to store real part of h[7] * (W8 ^ 3)
  reg signed [31:0] h7_prime_imag;  // 32 bit register to store imag part of h[7] * (W8 ^ 3)

  reg signed [15:0] h5_prime_real_16;  // 16 bit register to store real part of h[5] * (W8 ^ 1)
  reg signed [15:0] h5_prime_imag_16;  // 16 bit register to store imag part of h[5] * (W8 ^ 1)
  reg signed [15:0] h7_prime_real_16;  // 16 bit register to store real part of h[7] * (W8 ^ 3)
  reg signed [15:0] h7_prime_imag_16;  // 16 bit register to store imag part of h[7] * (W8 ^ 3)

  always @(posedge CLK) begin
		if (~RST_N) begin
			ready <= 1'b0;
			stage <= 2'b00;
      i_real[0] <= 0; i_imag[0]<=0;
      i_real[1] <= 0; i_imag[1]<=0;
      i_real[2] <= 0; i_imag[2]<=0;
      i_real[3] <= 0; i_imag[3]<=0;
      i_real[4] <= 0; i_imag[4]<=0;
      i_real[5] <= 0; i_imag[5]<=0;
      i_real[6] <= 0; i_imag[6]<=0;
      i_real[7] <= 0; i_imag[7]<=0;
		end
		else begin
			if (start) begin
				case(stage)
          3'b000: begin
            g_real[0] <= i0_real + i4_real;
            g_imag[0] <= i0_imag + i4_imag;
            g_real[1] <= i0_real - i4_real;
            g_imag[1] <= i0_imag - i4_imag;
            g_real[2] <= i2_real + i6_real;
            g_imag[2] <= i2_imag + i6_imag;
            g_real[3] <= i2_real - i6_real;
            g_imag[3] <= i2_imag - i6_imag;
            g_real[4] <= i1_real + i5_real;
            g_imag[4] <= i1_imag + i5_imag;
            g_real[5] <= i1_real - i5_real;
            g_imag[5] <= i1_imag - i5_imag;
            g_real[6] <= i3_real + i7_real;
            g_imag[6] <= i3_imag + i7_imag;
            g_real[7] <= i3_real - i7_real;
            g_imag[7] <= i3_imag - i7_imag; 
          end
          3'b001:begin
            h_real[0] <= g_real[0] + g_real[2];        // h0_real = g0_real + g2_real
            h_imag[0] <= g_imag[0] + g_imag[2];        // h0_imag = g0_imag + g2_imag
            h_real[1] <= g_real[1] + g_imag[3];   // h1_real = g1_real - (j*g3_real)  
            h_imag[1] <= g_imag[1] - g_real[3];        // h1_imag = g1_imag - (j*g3_imag)
            h_real[2] <= g_real[0] - g_real[2];        // h2_real = g0_real - g2_real
            h_imag[2] <= g_imag[0] - g_imag[2];        // h2_imag = g0_imag - g2_imag
            h_real[3] <= g_real[1] - g_imag[3];   // h3_real = g1_real + (j*g3_real)
            h_imag[3] <= g_imag[1] + g_real[3];        // h3_imag = g1_imag + (j*g3_imag)
            h_real[4] <= g_real[4] + g_real[6];        // h4_real = g4_real + g6_real
            h_imag[4] <= g_imag[4] + g_imag[6];        // h4_imag = g4_imag + g6_imag
            h_real[5] <= g_real[5] + g_imag[7];   // h5_real = g5_real - (j*g7_real)
            h_imag[5] <= g_imag[5] - g_real[7];        // h5_imag = g5_imag - (j*g7_imag)
            h_real[6] <= g_real[4] - g_real[6];        // h6_real = g4_real - g6_real
            h_imag[6] <= g_imag[4] - g_imag[6];        // h6_imag = g4_imag - g6_imag
            h_real[7] <= g_real[5] - g_imag[7];   // h7_real = g5_real + (j*g7_real)
            h_imag[7] <= g_imag[5] + g_real[7];        // h7_imag = g5_imag + (j*g7_imag)
          end
          3'b010:begin
            temp0 <= h_real[5] + h_imag[5];
            temp1 <= h_imag[5] - h_real[5];
            temp2 <= h_imag[7] - h_real[7];
            temp3 <= (-(h_imag[7] + h_real[7]));
          end
          3'b011:begin
            h5_prime_real <= temp0 * 16'b0000000010110100;
            h5_prime_imag <= temp1 * 16'b0000000010110100;
            h7_prime_real <= temp2 * 16'b0000000010110100;
            h7_prime_imag <= temp3 * 16'b0000000010110100;
          end
          3'b100:begin
            i_real[0] <= h_real[0] + h_real[4];  // i0_real = h0_real + h4_real
            i_imag[0] <= h_imag[0] + h_imag[4];  // i0_imag = h0_imag + h4_imag
            i_real[1] <= h_real[1] + h5_prime_real_16;  // i1_real = h[1]_real + Re((W8 ^ 1)*h[5])
            i_imag[1] <= h_imag[1] + h5_prime_imag_16;  // i1_imag = h[1]_imag + Im((W8 ^ 1)*h[5])
            i_real[2] <= h_real[2] + h_imag[6];  // i2_real = h2_real - (j*h6_real)
            i_imag[2] <= h_imag[2] - h_real[6];  // i2_imag = h2_imag - (j*h6_imag)
            i_real[3] <= h_real[3] + h7_prime_real_16;  // i3_real = h[3]_real + Re((W8^3)*h[7])
            i_imag[3] <= h_imag[3] + h7_prime_imag_16;  // i3_imag = h[3]_imag + Im((W8^3)*h[7]) 
            i_real[4] <= h_real[0] - h_real[4];  // i4_real = h0_real - h4_real
            i_imag[4] <= h_imag[0] - h_imag[4];  // i4_imag = h0_imag - h4_imag
            i_real[5] <= h_real[1] - h5_prime_real_16;  // i5_real = h[1]_real - Re((W8^1)*h[5])
            i_imag[5] <= h_imag[1] - h5_prime_imag_16;  // i5_imag = h[1]_imag - Im((W8^1)*h[5])
            i_real[6] <= h_real[2] - h_imag[6];  // i6_real = h2_real + (j*h6_real)
            i_imag[6] <= h_imag[2] + h_real[6];  // i6_imag = h2_imag + (j*h6_imag)
            i_real[7] <= h_real[3] - h7_prime_real_16;  // i7_real = h[3]_real - Re((W8^3)*h[7])
            i_imag[7] <= h_imag[3] - h7_prime_imag_16;  // i7_imag = h[3]_imag - Im((W8^3)*h[7])
            ready <= 1'b1;
          end
        endcase
				stage <= stage + 2'b01;
			end
			else begin
				if (write) begin
          i0_real<= in0_real;  i0_imag <= in0_imag;
          i1_real<= in1_real;  i1_imag <= in1_imag;
          i2_real<= in2_real;  i2_imag <= in2_imag;
          i3_real<= in3_real;  i3_imag <= in3_imag;
          i4_real<= in4_real;  i4_imag <= in4_imag;
          i5_real<= in5_real;  i5_imag <= in5_imag;
          i6_real<= in6_real;  i6_imag <= in6_imag;
          i7_real<= in7_real;  i7_imag <= in7_imag;
				end
				ready <= 1'b0;
			end
		end
	end

always@(*) begin
  h5_prime_real_16 <= h5_prime_real[23:8];
  h5_prime_imag_16 <= h5_prime_imag[23:8];
  h7_prime_real_16 <= h7_prime_real[23:8];
  h7_prime_imag_16 <= h7_prime_imag[23:8];
end

  assign out0_real = i_real[0]; assign out0_imag = i_imag[0];
  assign out1_real = i_real[1]; assign out1_imag = i_imag[1];
  assign out2_real = i_real[2]; assign out2_imag = i_imag[2];
  assign out3_real = i_real[3]; assign out3_imag = i_imag[3];
  assign out4_real = i_real[4]; assign out4_imag = i_imag[4];
  assign out5_real = i_real[5]; assign out5_imag = i_imag[5];
  assign out6_real = i_real[6]; assign out6_imag = i_imag[6];
  assign out7_real = i_real[7]; assign out7_imag = i_imag[7];

endmodule

fft_tb.v
`include "fft.v"
`timescale 1ns/1ps

module fft_tb();

	parameter CLOCK_PERIOD = 100; // 10 MHz clock

    reg sys_clk, sys_rst_n;
	reg write, start;

	reg signed [15:0]  in0_real  ,in0_imag;
	reg signed [15:0]  in1_real  ,in1_imag;
	reg signed [15:0]  in2_real  ,in2_imag;
	reg signed [15:0]  in3_real  ,in3_imag;
	reg signed [15:0]  in4_real  ,in4_imag;
	reg signed [15:0]  in5_real  ,in5_imag;
	reg signed [15:0]  in6_real  ,in6_imag;
	reg signed [15:0]  in7_real  ,in7_imag;
	wire ready;

	wire signed [15:0] out0_real ,out0_imag;
	wire signed [15:0] out1_real ,out1_imag;
	wire signed [15:0] out2_real ,out2_imag;
	wire signed [15:0] out3_real ,out3_imag;
	wire signed [15:0] out4_real ,out4_imag;
	wire signed [15:0] out5_real ,out5_imag;
	wire signed [15:0] out6_real ,out6_imag;
	wire signed [15:0] out7_real ,out7_imag;

	fft DUT(.CLK(sys_clk), .RST_N(sys_rst_n), .write(write), .start(start), .in0_real(in0_real) , .in0_imag(in0_imag), .in1_real(in1_real), .in1_imag(in1_imag), 
 .in2_real(in2_real)  ,.in2_imag(in2_imag), .in3_real(in3_real)  ,.in3_imag(in3_imag), .in4_real(in4_real)  ,.in4_imag(in4_imag), .in5_real(in5_real)  ,.in5_imag(in5_imag),
 .in6_real(in6_real)  ,.in6_imag(in6_imag), .in7_real(in7_real)  ,.in7_imag(in7_imag), .ready(ready), .out0_real(out0_real) ,.out0_imag(out0_imag), .out1_real(out1_real), 
 .out1_imag(out1_imag), .out2_real(out2_real) ,.out2_imag(out2_imag), .out3_real(out3_real) ,.out3_imag(out3_imag), .out4_real(out4_real) ,.out4_imag(out4_imag), 
 .out5_real(out5_real) ,.out5_imag(out5_imag), .out6_real(out6_real) ,.out6_imag(out6_imag), .out7_real(out7_real) ,.out7_imag(out7_imag));

	// VCD dump
	initial begin
		$dumpfile("fft.vcd");
		$dumpvars(0, DUT);
	end

	// System clock generator
	always begin
		#(CLOCK_PERIOD/2) sys_clk = ~sys_clk;
	end

    // Initial Condition
    initial begin
		sys_clk = 1'b0; sys_rst_n = 1'b0;
		write = 1'b0; start = 1'b0;
		in0_real=16'h00_00  ;in0_imag = 0;
		in1_real=16'h01_00  ;in1_imag = 0;
		in2_real=16'h02_00  ;in2_imag = 0;
		in3_real=16'h03_00  ;in3_imag = 0;
		in4_real=16'h04_00  ;in4_imag = 0;
		in5_real=16'h05_00  ;in5_imag = 0;
		in6_real=16'h06_00  ;in6_imag = 0;
		in7_real=16'h07_00  ;in7_imag = 0;
		#CLOCK_PERIOD sys_rst_n = 1'b1;
		#CLOCK_PERIOD write = 1'b1;
		#CLOCK_PERIOD start = 1'b1;
		#(CLOCK_PERIOD/2) $display("START OF SIMULATION (Time: %g ns)", $time);
		#10000;
		$finish;
	end

endmodule

fft.vcd
$date
	Wed Nov 15 22:11:39 2023
$end
$version
	Icarus Verilog
$end
$timescale
	1ps
$end
$scope module fft_tb $end
$scope module DUT $end
$var wire 1 ! CLK $end
$var wire 1 " RST_N $end
$var wire 16 # in0_imag [15:0] $end
$var wire 16 $ in0_real [15:0] $end
$var wire 16 % in1_imag [15:0] $end
$var wire 16 & in1_real [15:0] $end
$var wire 16 ' in2_imag [15:0] $end
$var wire 16 ( in2_real [15:0] $end
$var wire 16 ) in3_imag [15:0] $end
$var wire 16 * in3_real [15:0] $end
$var wire 16 + in4_imag [15:0] $end
$var wire 16 , in4_real [15:0] $end
$var wire 16 - in5_imag [15:0] $end
$var wire 16 . in5_real [15:0] $end
$var wire 16 / in6_imag [15:0] $end
$var wire 16 0 in6_real [15:0] $end
$var wire 16 1 in7_imag [15:0] $end
$var wire 16 2 in7_real [15:0] $end
$var wire 16 3 out0_imag [15:0] $end
$var wire 16 4 out0_real [15:0] $end
$var wire 16 5 out1_imag [15:0] $end
$var wire 16 6 out1_real [15:0] $end
$var wire 16 7 out2_imag [15:0] $end
$var wire 16 8 out2_real [15:0] $end
$var wire 16 9 out3_imag [15:0] $end
$var wire 16 : out3_real [15:0] $end
$var wire 16 ; out4_imag [15:0] $end
$var wire 16 < out4_real [15:0] $end
$var wire 16 = out5_imag [15:0] $end
$var wire 16 > out5_real [15:0] $end
$var wire 16 ? out6_imag [15:0] $end
$var wire 16 @ out6_real [15:0] $end
$var wire 16 A out7_imag [15:0] $end
$var wire 16 B out7_real [15:0] $end
$var wire 1 C start $end
$var wire 1 D write $end
$var reg 32 E h5_prime_imag [31:0] $end
$var reg 16 F h5_prime_imag_16 [15:0] $end
$var reg 32 G h5_prime_real [31:0] $end
$var reg 16 H h5_prime_real_16 [15:0] $end
$var reg 32 I h7_prime_imag [31:0] $end
$var reg 16 J h7_prime_imag_16 [15:0] $end
$var reg 32 K h7_prime_real [31:0] $end
$var reg 16 L h7_prime_real_16 [15:0] $end
$var reg 16 M i0_imag [15:0] $end
$var reg 16 N i0_real [15:0] $end
$var reg 16 O i1_imag [15:0] $end
$var reg 16 P i1_real [15:0] $end
$var reg 16 Q i2_imag [15:0] $end
$var reg 16 R i2_real [15:0] $end
$var reg 16 S i3_imag [15:0] $end
$var reg 16 T i3_real [15:0] $end
$var reg 16 U i4_imag [15:0] $end
$var reg 16 V i4_real [15:0] $end
$var reg 16 W i5_imag [15:0] $end
$var reg 16 X i5_real [15:0] $end
$var reg 16 Y i6_imag [15:0] $end
$var reg 16 Z i6_real [15:0] $end
$var reg 16 [ i7_imag [15:0] $end
$var reg 16 \ i7_real [15:0] $end
$var reg 1 ] ready $end
$var reg 3 ^ stage [2:0] $end
$var reg 16 _ temp0 [15:0] $end
$var reg 16 ` temp1 [15:0] $end
$var reg 16 a temp2 [15:0] $end
$var reg 16 b temp3 [15:0] $end
$upscope $end
$upscope $end
$enddefinitions $end
$comment Show the parameter values. $end
$dumpall
$end
#0
$dumpvars
bx b
bx a
bx `
bx _
bx ^
x]
bx \
bx [
bx Z
bx Y
bx X
bx W
bx V
bx U
bx T
bx S
bx R
bx Q
bx P
bx O
bx N
bx M
bx L
bx K
bx J
bx I
bx H
bx G
bx F
bx E
0D
0C
bx B
bx A
bx @
bx ?
bx >
bx =
bx <
bx ;
bx :
bx 9
bx 8
bx 7
bx 6
bx 5
bx 4
bx 3
b11100000000 2
b0 1
b11000000000 0
b0 /
b10100000000 .
b0 -
b10000000000 ,
b0 +
b1100000000 *
b0 )
b1000000000 (
b0 '
b100000000 &
b0 %
b0 $
b0 #
0"
0!
$end
#50000
b0 A
b0 B
b0 ?
b0 @
b0 =
b0 >
b0 ;
b0 <
b0 9
b0 :
b0 7
b0 8
b0 5
b0 6
b0 3
b0 4
b0 ^
0]
1!
#100000
0!
1"
#150000
1!
#200000
0!
1D
#250000
b0 [
b11100000000 \
b0 Y
b11000000000 Z
b0 W
b10100000000 X
b0 U
b10000000000 V
b0 S
b1100000000 T
b0 Q
b1000000000 R
b0 O
b100000000 P
b0 M
b0 N
1!
#300000
0!
1C
#350000
b1 ^
1!
#400000
0!
#450000
b10 ^
1!
#500000
0!
#550000
b11 ^
b100000000000 b
b0 a
b100000000000 `
b0 _
1!
#600000
0!
#650000
b10110100000 J
b0 L
b10110100000 F
b0 H
b100 ^
b1011010000000000000 I
b0 K
b1011010000000000000 E
b0 G
1!
#700000
0!
#750000
b101 ^
1]
b1111011001100000 A
b1111110000000000 B
b1111110000000000 ?
b1111110000000000 @
b1111111001100000 =
b1111110000000000 >
b1111110000000000 <
b110100000 9
b1111110000000000 :
b10000000000 7
b1111110000000000 8
b100110100000 5
b1111110000000000 6
b1110000000000 4
1!
#800000
0!
#850000
b110 ^
1!
#900000
0!
#950000
b111 ^
1!
#1000000
0!
#1050000
b0 ^
1!
#1100000
0!
#1150000
b1 ^
1!
#1200000
0!
#1250000
b10 ^
1!
#1300000
0!
#1350000
b11 ^
1!
#1400000
0!
#1450000
b100 ^
1!
#1500000
0!
#1550000
b101 ^
1!
#1600000
0!
#1650000
b110 ^
1!
#1700000
0!
#1750000
b111 ^
1!
#1800000
0!
#1850000
b0 ^
1!
#1900000
0!
#1950000
b1 ^
1!
#2000000
0!
#2050000
b10 ^
1!
#2100000
0!
#2150000
b11 ^
1!
#2200000
0!
#2250000
b100 ^
1!
#2300000
0!
#2350000
b101 ^
1!
#2400000
0!
#2450000
b110 ^
1!
#2500000
0!
#2550000
b111 ^
1!
#2600000
0!
#2650000
b0 ^
1!
#2700000
0!
#2750000
b1 ^
1!
#2800000
0!
#2850000
b10 ^
1!
#2900000
0!
#2950000
b11 ^
1!
#3000000
0!
#3050000
b100 ^
1!
#3100000
0!
#3150000
b101 ^
1!
#3200000
0!
#3250000
b110 ^
1!
#3300000
0!
#3350000
b111 ^
1!
#3400000
0!
#3450000
b0 ^
1!
#3500000
0!
#3550000
b1 ^
1!
#3600000
0!
#3650000
b10 ^
1!
#3700000
0!
#3750000
b11 ^
1!
#3800000
0!
#3850000
b100 ^
1!
#3900000
0!
#3950000
b101 ^
1!
#4000000
0!
#4050000
b110 ^
1!
#4100000
0!
#4150000
b111 ^
1!
#4200000
0!
#4250000
b0 ^
1!
#4300000
0!
#4350000
b1 ^
1!
#4400000
0!
#4450000
b10 ^
1!
#4500000
0!
#4550000
b11 ^
1!
#4600000
0!
#4650000
b100 ^
1!
#4700000
0!
#4750000
b101 ^
1!
#4800000
0!
#4850000
b110 ^
1!
#4900000
0!
#4950000
b111 ^
1!
#5000000
0!
#5050000
b0 ^
1!
#5100000
0!
#5150000
b1 ^
1!
#5200000
0!
#5250000
b10 ^
1!
#5300000
0!
#5350000
b11 ^
1!
#5400000
0!
#5450000
b100 ^
1!
#5500000
0!
#5550000
b101 ^
1!
#5600000
0!
#5650000
b110 ^
1!
#5700000
0!
#5750000
b111 ^
1!
#5800000
0!
#5850000
b0 ^
1!
#5900000
0!
#5950000
b1 ^
1!
#6000000
0!
#6050000
b10 ^
1!
#6100000
0!
#6150000
b11 ^
1!
#6200000
0!
#6250000
b100 ^
1!
#6300000
0!
#6350000
b101 ^
1!
#6400000
0!
#6450000
b110 ^
1!
#6500000
0!
#6550000
b111 ^
1!
#6600000
0!
#6650000
b0 ^
1!
#6700000
0!
#6750000
b1 ^
1!
#6800000
0!
#6850000
b10 ^
1!
#6900000
0!
#6950000
b11 ^
1!
#7000000
0!
#7050000
b100 ^
1!
#7100000
0!
#7150000
b101 ^
1!
#7200000
0!
#7250000
b110 ^
1!
#7300000
0!
#7350000
b111 ^
1!
#7400000
0!
#7450000
b0 ^
1!
#7500000
0!
#7550000
b1 ^
1!
#7600000
0!
#7650000
b10 ^
1!
#7700000
0!
#7750000
b11 ^
1!
#7800000
0!
#7850000
b100 ^
1!
#7900000
0!
#7950000
b101 ^
1!
#8000000
0!
#8050000
b110 ^
1!
#8100000
0!
#8150000
b111 ^
1!
#8200000
0!
#8250000
b0 ^
1!
#8300000
0!
#8350000
b1 ^
1!
#8400000
0!
#8450000
b10 ^
1!
#8500000
0!
#8550000
b11 ^
1!
#8600000
0!
#8650000
b100 ^
1!
#8700000
0!
#8750000
b101 ^
1!
#8800000
0!
#8850000
b110 ^
1!
#8900000
0!
#8950000
b111 ^
1!
#9000000
0!
#9050000
b0 ^
1!
#9100000
0!
#9150000
b1 ^
1!
#9200000
0!
#9250000
b10 ^
1!
#9300000
0!
#9350000
b11 ^
1!
#9400000
0!
#9450000
b100 ^
1!
#9500000
0!
#9550000
b101 ^
1!
#9600000
0!
#9650000
b110 ^
1!
#9700000
0!
#9750000
b111 ^
1!
#9800000
0!
#9850000
b0 ^
1!
#9900000
0!
#9950000
b1 ^
1!
#10000000
0!
#10050000
b10 ^
1!
#10100000
0!
#10150000
b11 ^
1!
#10200000
0!
#10250000
b100 ^
1!
#10300000
0!
#10350000
b101 ^
1!
