fft.v
module fft(CLK, RST_N, write, start, in0_real , in0_imag, in1_real, in1_imag, 
 in2_real  ,in2_imag, in3_real  ,in3_imag, in4_real  ,in4_imag, in5_real  ,in5_imag,
 in6_real  ,in6_imag, in7_real  ,in7_imag, ready, out0_real ,out0_imag, out1_real, 
 out1_imag, out2_real ,out2_imag, out3_real ,out3_imag, out4_real ,out4_imag, 
 out5_real ,out5_imag, out6_real ,out6_imag, out7_real ,out7_imag);

  input CLK, RST_N;
  input write, start;
  input wire signed [15:0]  in0_real  ,in0_imag;
  input wire signed [15:0]  in1_real  ,in1_imag;
  input wire signed [15:0]  in2_real  ,in2_imag;
  input wire signed [15:0]  in3_real  ,in3_imag;
  input wire signed [15:0]  in4_real  ,in4_imag;
  input wire signed [15:0]  in5_real  ,in5_imag;
  input wire signed [15:0]  in6_real  ,in6_imag;
  input wire signed [15:0]  in7_real  ,in7_imag;
  output reg ready;
  output wire signed [15:0] out0_real ,out0_imag;
  output wire signed [15:0] out1_real ,out1_imag;
  output wire signed [15:0] out2_real ,out2_imag;
  output wire signed [15:0] out3_real ,out3_imag;
  output wire signed [15:0] out4_real ,out4_imag;
  output wire signed [15:0] out5_real ,out5_imag;
  output wire signed [15:0] out6_real ,out6_imag;
  output wire signed [15:0] out7_real ,out7_imag;

  reg signed [15:0] i0_real, i0_imag;
  reg signed [15:0] i1_real, i1_imag;
  reg signed [15:0] i2_real, i2_imag;
  reg signed [15:0] i3_real, i3_imag;
  reg signed [15:0] i4_real, i4_imag;
  reg signed [15:0] i5_real, i5_imag;
  reg signed [15:0] i6_real, i6_imag;
  reg signed [15:0] i7_real, i7_imag;
  reg [2:0] stage;

  reg signed [15:0] g_real [0:7];   // Declare g_real as an array of registers to store real part of stage 1 results
  reg signed [15:0] g_imag [0:7];   // Declare g_imag as an array of registers to store imag part of stage 1 results
  reg signed [15:0] h_real [0:7];   // Declare h_real as an array of registers to store real part of stage 2 results
  reg signed [15:0] h_imag [0:7];   // Declare h_imag as an array of registers to store imag part of stage 2 results
  reg signed [15:0] i_real [0:7];   // Declare i_real as an array of registers to store real part of stage 3 results
  reg signed [15:0] i_imag [0:7];   // Declare i_imag as an array of registers to store imag part of stage 3 results

  reg signed [15:0] temp1,temp2,temp3,temp0;
  reg signed [31:0] h5_prime_real;  // 32 bit register to store real part of h[5] * (W8 ^ 1)
  reg signed [31:0] h5_prime_imag;  // 32 bit register to store imag part of h[5] * (W8 ^ 1)
  reg signed [31:0] h7_prime_real;  // 32 bit register to store real part of h[7] * (W8 ^ 3)
  reg signed [31:0] h7_prime_imag;  // 32 bit register to store imag part of h[7] * (W8 ^ 3)

  reg signed [15:0] h5_prime_real_16;  // 16 bit register to store real part of h[5] * (W8 ^ 1)
  reg signed [15:0] h5_prime_imag_16;  // 16 bit register to store imag part of h[5] * (W8 ^ 1)
  reg signed [15:0] h7_prime_real_16;  // 16 bit register to store real part of h[7] * (W8 ^ 3)
  reg signed [15:0] h7_prime_imag_16;  // 16 bit register to store imag part of h[7] * (W8 ^ 3)

  always @(posedge CLK) begin
		if (~RST_N) begin
			ready <= 1'b0;
			stage <= 2'b00;
      i_real[0] <= 0; i_imag[0]<=0;
      i_real[1] <= 0; i_imag[1]<=0;
      i_real[2] <= 0; i_imag[2]<=0;
      i_real[3] <= 0; i_imag[3]<=0;
      i_real[4] <= 0; i_imag[4]<=0;
      i_real[5] <= 0; i_imag[5]<=0;
      i_real[6] <= 0; i_imag[6]<=0;
      i_real[7] <= 0; i_imag[7]<=0;
		end
		else begin
			if (start) begin
				case(stage)
          3'b000: begin
            g_real[0] <= i0_real + i4_real;
            g_imag[0] <= i0_imag + i4_imag;
            g_real[1] <= i0_real - i4_real;
            g_imag[1] <= i0_imag - i4_imag;
            g_real[2] <= i2_real + i6_real;
            g_imag[2] <= i2_imag + i6_imag;
            g_real[3] <= i2_real - i6_real;
            g_imag[3] <= i2_imag - i6_imag;
            g_real[4] <= i1_real + i5_real;
            g_imag[4] <= i1_imag + i5_imag;
            g_real[5] <= i1_real - i5_real;
            g_imag[5] <= i1_imag - i5_imag;
            g_real[6] <= i3_real + i7_real;
            g_imag[6] <= i3_imag + i7_imag;
            g_real[7] <= i3_real - i7_real;
            g_imag[7] <= i3_imag - i7_imag; 
          end
          3'b001:begin
            h_real[0] <= g_real[0] + g_real[2];        // h0_real = g0_real + g2_real
            h_imag[0] <= g_imag[0] + g_imag[2];        // h0_imag = g0_imag + g2_imag
            h_real[1] <= g_real[1] + g_imag[3];   // h1_real = g1_real - (j*g3_real)  
            h_imag[1] <= g_imag[1] - g_real[3];        // h1_imag = g1_imag - (j*g3_imag)
            h_real[2] <= g_real[0] - g_real[2];        // h2_real = g0_real - g2_real
            h_imag[2] <= g_imag[0] - g_imag[2];        // h2_imag = g0_imag - g2_imag
            h_real[3] <= g_real[1] - g_imag[3];   // h3_real = g1_real + (j*g3_real)
            h_imag[3] <= g_imag[1] + g_real[3];        // h3_imag = g1_imag + (j*g3_imag)
            h_real[4] <= g_real[4] + g_real[6];        // h4_real = g4_real + g6_real
            h_imag[4] <= g_imag[4] + g_imag[6];        // h4_imag = g4_imag + g6_imag
            h_real[5] <= g_real[5] + g_imag[7];   // h5_real = g5_real - (j*g7_real)
            h_imag[5] <= g_imag[5] - g_real[7];        // h5_imag = g5_imag - (j*g7_imag)
            h_real[6] <= g_real[4] - g_real[6];        // h6_real = g4_real - g6_real
            h_imag[6] <= g_imag[4] - g_imag[6];        // h6_imag = g4_imag - g6_imag
            h_real[7] <= g_real[5] - g_imag[7];   // h7_real = g5_real + (j*g7_real)
            h_imag[7] <= g_imag[5] + g_real[7];        // h7_imag = g5_imag + (j*g7_imag)
          end
          3'b010:begin
            temp0 <= h_real[5] + h_imag[5];
            temp1 <= h_imag[5] - h_real[5];
            temp2 <= h_imag[7] - h_real[7];
            temp3 <= (-(h_imag[7] + h_real[7]));
          end
          3'b011:begin
            h5_prime_real <= temp0 * 16'b0000000010110100;
            h5_prime_imag <= temp1 * 16'b0000000010110100;
            h7_prime_real <= temp2 * 16'b0000000010110100;
            h7_prime_imag <= temp3 * 16'b0000000010110100;
          end
          3'b100:begin
            i_real[0] <= h_real[0] + h_real[4];  // i0_real = h0_real + h4_real
            i_imag[0] <= h_imag[0] + h_imag[4];  // i0_imag = h0_imag + h4_imag
            i_real[1] <= h_real[1] + h5_prime_real_16;  // i1_real = h[1]_real + Re((W8 ^ 1)*h[5])
            i_imag[1] <= h_imag[1] + h5_prime_imag_16;  // i1_imag = h[1]_imag + Im((W8 ^ 1)*h[5])
            i_real[2] <= h_real[2] + h_imag[6];  // i2_real = h2_real - (j*h6_real)
            i_imag[2] <= h_imag[2] - h_real[6];  // i2_imag = h2_imag - (j*h6_imag)
            i_real[3] <= h_real[3] + h7_prime_real_16;  // i3_real = h[3]_real + Re((W8^3)*h[7])
            i_imag[3] <= h_imag[3] + h7_prime_imag_16;  // i3_imag = h[3]_imag + Im((W8^3)*h[7]) 
            i_real[4] <= h_real[0] - h_real[4];  // i4_real = h0_real - h4_real
            i_imag[4] <= h_imag[0] - h_imag[4];  // i4_imag = h0_imag - h4_imag
            i_real[5] <= h_real[1] - h5_prime_real_16;  // i5_real = h[1]_real - Re((W8^1)*h[5])
            i_imag[5] <= h_imag[1] - h5_prime_imag_16;  // i5_imag = h[1]_imag - Im((W8^1)*h[5])
            i_real[6] <= h_real[2] - h_imag[6];  // i6_real = h2_real + (j*h6_real)
            i_imag[6] <= h_imag[2] + h_real[6];  // i6_imag = h2_imag + (j*h6_imag)
            i_real[7] <= h_real[3] - h7_prime_real_16;  // i7_real = h[3]_real - Re((W8^3)*h[7])
            i_imag[7] <= h_imag[3] - h7_prime_imag_16;  // i7_imag = h[3]_imag - Im((W8^3)*h[7])
            ready <= 1'b1;
          end
        endcase
				stage <= stage + 2'b01;
			end
			else begin
				if (write) begin
          i0_real<= in0_real;  i0_imag <= in0_imag;
          i1_real<= in1_real;  i1_imag <= in1_imag;
          i2_real<= in2_real;  i2_imag <= in2_imag;
          i3_real<= in3_real;  i3_imag <= in3_imag;
          i4_real<= in4_real;  i4_imag <= in4_imag;
          i5_real<= in5_real;  i5_imag <= in5_imag;
          i6_real<= in6_real;  i6_imag <= in6_imag;
          i7_real<= in7_real;  i7_imag <= in7_imag;
				end
				ready <= 1'b0;
			end
		end
	end

always@(*) begin
  h5_prime_real_16 <= h5_prime_real[23:8];
  h5_prime_imag_16 <= h5_prime_imag[23:8];
  h7_prime_real_16 <= h7_prime_real[23:8];
  h7_prime_imag_16 <= h7_prime_imag[23:8];
end

  assign out0_real = i_real[0]; assign out0_imag = i_imag[0];
  assign out1_real = i_real[1]; assign out1_imag = i_imag[1];
  assign out2_real = i_real[2]; assign out2_imag = i_imag[2];
  assign out3_real = i_real[3]; assign out3_imag = i_imag[3];
  assign out4_real = i_real[4]; assign out4_imag = i_imag[4];
  assign out5_real = i_real[5]; assign out5_imag = i_imag[5];
  assign out6_real = i_real[6]; assign out6_imag = i_imag[6];
  assign out7_real = i_real[7]; assign out7_imag = i_imag[7];

endmodule

fft_tb.v
`include "fft.v"
`timescale 1ns/1ps

module fft_tb();

	parameter CLOCK_PERIOD = 5; // 10 MHz clock

    reg sys_clk, sys_rst_n;
	reg write, start;

	reg signed [15:0]  in0_real  ,in0_imag;
	reg signed [15:0]  in1_real  ,in1_imag;
	reg signed [15:0]  in2_real  ,in2_imag;
	reg signed [15:0]  in3_real  ,in3_imag;
	reg signed [15:0]  in4_real  ,in4_imag;
	reg signed [15:0]  in5_real  ,in5_imag;
	reg signed [15:0]  in6_real  ,in6_imag;
	reg signed [15:0]  in7_real  ,in7_imag;
	wire ready;

	wire signed [15:0] out0_real ,out0_imag;
	wire signed [15:0] out1_real ,out1_imag;
	wire signed [15:0] out2_real ,out2_imag;
	wire signed [15:0] out3_real ,out3_imag;
	wire signed [15:0] out4_real ,out4_imag;
	wire signed [15:0] out5_real ,out5_imag;
	wire signed [15:0] out6_real ,out6_imag;
	wire signed [15:0] out7_real ,out7_imag;

	fft DUT(.CLK(sys_clk), .RST_N(sys_rst_n), .write(write), .start(start), .in0_real(in0_real) , .in0_imag(in0_imag), .in1_real(in1_real), .in1_imag(in1_imag), 
 .in2_real(in2_real)  ,.in2_imag(in2_imag), .in3_real(in3_real)  ,.in3_imag(in3_imag), .in4_real(in4_real)  ,.in4_imag(in4_imag), .in5_real(in5_real)  ,.in5_imag(in5_imag),
 .in6_real(in6_real)  ,.in6_imag(in6_imag), .in7_real(in7_real)  ,.in7_imag(in7_imag), .ready(ready), .out0_real(out0_real) ,.out0_imag(out0_imag), .out1_real(out1_real), 
 .out1_imag(out1_imag), .out2_real(out2_real) ,.out2_imag(out2_imag), .out3_real(out3_real) ,.out3_imag(out3_imag), .out4_real(out4_real) ,.out4_imag(out4_imag), 
 .out5_real(out5_real) ,.out5_imag(out5_imag), .out6_real(out6_real) ,.out6_imag(out6_imag), .out7_real(out7_real) ,.out7_imag(out7_imag));

	// VCD dump
	initial begin
		$dumpfile("fft.vcd");
		$dumpvars(0, DUT);
	end

	// System clock generator
	always begin
		#(CLOCK_PERIOD/2) sys_clk = ~sys_clk;
	end

    // Initial Condition
    initial begin
		sys_clk = 1'b0; sys_rst_n = 1'b0;
		write = 1'b0; start = 1'b0;
		in0_real=16'h00_00  ;in0_imag = 0;
		in1_real=16'h01_00  ;in1_imag = 0;
		in2_real=16'h02_00  ;in2_imag = 0;
		in3_real=16'h03_00  ;in3_imag = 0;
		in4_real=16'h04_00  ;in4_imag = 0;
		in5_real=16'h05_00  ;in5_imag = 0;
		in6_real=16'h06_00  ;in6_imag = 0;
		in7_real=16'h07_00  ;in7_imag = 0;
		#CLOCK_PERIOD sys_rst_n = 1'b1;
		#CLOCK_PERIOD write = 1'b1;
		#CLOCK_PERIOD start = 1'b1;
		#(CLOCK_PERIOD/2) $display("START OF SIMULATION (Time: %g ns)", $time);
		#10000;
		$finish;
	end

endmodule

fft.vcd
$date
	Thu Nov 23 17:52:40 2023
$end
$version
	Icarus Verilog
$end
$timescale
	1ps
$end
$scope module fft_tb $end
$scope module DUT $end
$var wire 1 ! CLK $end
$var wire 1 " RST_N $end
$var wire 16 # in0_imag [15:0] $end
$var wire 16 $ in0_real [15:0] $end
$var wire 16 % in1_imag [15:0] $end
$var wire 16 & in1_real [15:0] $end
$var wire 16 ' in2_imag [15:0] $end
$var wire 16 ( in2_real [15:0] $end
$var wire 16 ) in3_imag [15:0] $end
$var wire 16 * in3_real [15:0] $end
$var wire 16 + in4_imag [15:0] $end
$var wire 16 , in4_real [15:0] $end
$var wire 16 - in5_imag [15:0] $end
$var wire 16 . in5_real [15:0] $end
$var wire 16 / in6_imag [15:0] $end
$var wire 16 0 in6_real [15:0] $end
$var wire 16 1 in7_imag [15:0] $end
$var wire 16 2 in7_real [15:0] $end
$var wire 16 3 out0_imag [15:0] $end
$var wire 16 4 out0_real [15:0] $end
$var wire 16 5 out1_imag [15:0] $end
$var wire 16 6 out1_real [15:0] $end
$var wire 16 7 out2_imag [15:0] $end
$var wire 16 8 out2_real [15:0] $end
$var wire 16 9 out3_imag [15:0] $end
$var wire 16 : out3_real [15:0] $end
$var wire 16 ; out4_imag [15:0] $end
$var wire 16 < out4_real [15:0] $end
$var wire 16 = out5_imag [15:0] $end
$var wire 16 > out5_real [15:0] $end
$var wire 16 ? out6_imag [15:0] $end
$var wire 16 @ out6_real [15:0] $end
$var wire 16 A out7_imag [15:0] $end
$var wire 16 B out7_real [15:0] $end
$var wire 1 C start $end
$var wire 1 D write $end
$var reg 32 E h5_prime_imag [31:0] $end
$var reg 16 F h5_prime_imag_16 [15:0] $end
$var reg 32 G h5_prime_real [31:0] $end
$var reg 16 H h5_prime_real_16 [15:0] $end
$var reg 32 I h7_prime_imag [31:0] $end
$var reg 16 J h7_prime_imag_16 [15:0] $end
$var reg 32 K h7_prime_real [31:0] $end
$var reg 16 L h7_prime_real_16 [15:0] $end
$var reg 16 M i0_imag [15:0] $end
$var reg 16 N i0_real [15:0] $end
$var reg 16 O i1_imag [15:0] $end
$var reg 16 P i1_real [15:0] $end
$var reg 16 Q i2_imag [15:0] $end
$var reg 16 R i2_real [15:0] $end
$var reg 16 S i3_imag [15:0] $end
$var reg 16 T i3_real [15:0] $end
$var reg 16 U i4_imag [15:0] $end
$var reg 16 V i4_real [15:0] $end
$var reg 16 W i5_imag [15:0] $end
$var reg 16 X i5_real [15:0] $end
$var reg 16 Y i6_imag [15:0] $end
$var reg 16 Z i6_real [15:0] $end
$var reg 16 [ i7_imag [15:0] $end
$var reg 16 \ i7_real [15:0] $end
$var reg 1 ] ready $end
$var reg 3 ^ stage [2:0] $end
$var reg 16 _ temp0 [15:0] $end
$var reg 16 ` temp1 [15:0] $end
$var reg 16 a temp2 [15:0] $end
$var reg 16 b temp3 [15:0] $end
$upscope $end
$upscope $end
$enddefinitions $end
$comment Show the parameter values. $end
$dumpall
$end
#0
$dumpvars
bx b
bx a
bx `
bx _
bx ^
x]
bx \
bx [
bx Z
bx Y
bx X
bx W
bx V
bx U
bx T
bx S
bx R
bx Q
bx P
bx O
bx N
bx M
bx L
bx K
bx J
bx I
bx H
bx G
bx F
bx E
0D
0C
bx B
bx A
bx @
bx ?
bx >
bx =
bx <
bx ;
bx :
bx 9
bx 8
bx 7
bx 6
bx 5
bx 4
bx 3
b11100000000 2
b0 1
b11000000000 0
b0 /
b10100000000 .
b0 -
b10000000000 ,
b0 +
b1100000000 *
b0 )
b1000000000 (
b0 '
b100000000 &
b0 %
b0 $
b0 #
0"
0!
$end
#2000
b0 A
b0 B
b0 ?
b0 @
b0 =
b0 >
b0 ;
b0 <
b0 9
b0 :
b0 7
b0 8
b0 5
b0 6
b0 3
b0 4
b0 ^
0]
1!
#4000
0!
#5000
1"
#6000
1!
#8000
0!
#10000
b0 [
b11100000000 \
b0 Y
b11000000000 Z
b0 W
b10100000000 X
b0 U
b10000000000 V
b0 S
b1100000000 T
b0 Q
b1000000000 R
b0 O
b100000000 P
b0 M
b0 N
1!
1D
#12000
0!
#14000
1!
#15000
1C
#16000
0!
#18000
b1 ^
1!
#20000
0!
#22000
b10 ^
1!
#24000
0!
#26000
b11 ^
b100000000000 b
b0 a
b100000000000 `
b0 _
1!
#28000
0!
#30000
b10110100000 J
b0 L
b10110100000 F
b0 H
b100 ^
b1011010000000000000 I
b0 K
b1011010000000000000 E
b0 G
1!
#32000
0!
#34000
b101 ^
1]
b1111011001100000 A
b1111110000000000 B
b1111110000000000 ?
b1111110000000000 @
b1111111001100000 =
b1111110000000000 >
b1111110000000000 <
b110100000 9
b1111110000000000 :
b10000000000 7
b1111110000000000 8
b100110100000 5
b1111110000000000 6
b1110000000000 4
1!
#36000
0!
#38000
b110 ^
1!
#40000
0!
#42000
b111 ^
1!
#44000
0!
#46000
b0 ^
1!
#48000
0!
#50000
b1 ^
1!
#52000
0!
#54000
b10 ^
1!
#56000
0!
#58000
b11 ^
1!
#60000
0!
#62000
b100 ^
1!
#64000
0!
#66000
b101 ^
1!
#68000
0!
#70000
b110 ^
1!
#72000
0!
#74000
b111 ^
1!
#76000
0!
#78000
b0 ^
1!
#80000
0!
#82000
b1 ^
1!
#84000
0!
#86000
b10 ^
1!
#88000
0!
#90000
b11 ^
1!
#92000
0!
#94000
b100 ^
1!
#96000
0!
#98000
b101 ^
1!
#100000
0!
#102000
b110 ^
1!
#104000
0!
#106000
b111 ^
1!
#108000
0!
#110000
b0 ^
1!
#112000
0!
#114000
b1 ^
1!
#116000
0!
#118000
b10 ^
1!
#120000
0!
#122000
b11 ^
1!
#124000
0!
#126000
b100 ^
1!
#128000
0!
#130000
b101 ^
1!
#132000
0!
#134000
b110 ^
1!
#136000
0!
#138000
b111 ^
1!
#140000
0!
#142000
b0 ^
1!
#144000
0!
#146000
b1 ^
1!
#148000
0!
#150000
b10 ^
1!
#152000
0!
#154000
b11 ^
1!
#156000
0!
#158000
b100 ^
1!
#160000
0!
#162000
b101 ^
1!
#164000
0!
#166000
b110 ^
1!
#168000
0!
#170000
b111 ^
1!
#172000
0!
#174000
b0 ^
1!
#176000
0!
#178000
b1 ^
1!
#180000
0!
#182000
b10 ^
1!
#184000
0!
#186000
b11 ^
1!
#188000
0!
#190000
b100 ^
1!
#192000
0!
#194000
b101 ^
1!
#196000
0!
#198000
b110 ^
1!
#200000
0!
#202000
b111 ^
1!
#204000
0!
#206000
b0 ^
1!
#208000
0!
#210000
b1 ^
1!
#212000
0!
#214000
b10 ^
1!
#216000
0!
#218000
b11 ^
1!
#220000
0!
#222000
b100 ^
1!
#224000
0!
#226000
b101 ^
1!
#228000
0!
#230000
b110 ^
1!
#232000
0!
#234000
b111 ^
1!
#236000
0!
#238000
b0 ^
1!
#240000
0!
#242000
b1 ^
1!
#244000
0!
#246000
b10 ^
1!
#248000
0!
#250000
b11 ^
1!
#252000
0!
#254000
b100 ^
1!
#256000
0!
#258000
b101 ^
1!
#260000
0!
#262000
b110 ^
1!
#264000
0!
#266000
b111 ^
1!
#268000
0!
#270000
b0 ^
1!
#272000
0!
#274000
b1 ^
1!
#276000
0!
#278000
b10 ^
1!
#280000
0!
#282000
b11 ^
1!
#284000
0!
#286000
b100 ^
1!
#288000
0!
#290000
b101 ^
1!
#292000
0!
#294000
b110 ^
1!
#296000
0!
#298000
b111 ^
1!
#300000
0!
#302000
b0 ^
1!
#304000
0!
#306000
b1 ^
1!
#308000
0!
#310000
b10 ^
1!
#312000
0!
#314000
b11 ^
1!
#316000
0!
#318000
b100 ^
1!
#320000
0!
#322000
b101 ^
1!
#324000
0!
#326000
b110 ^
1!
#328000
0!
#330000
b111 ^
1!
#332000
0!
#334000
b0 ^
1!
#336000
0!
#338000
b1 ^
1!
#340000
0!
#342000
b10 ^
1!
#344000
0!
#346000
b11 ^
1!
#348000
0!
#350000
b100 ^
1!
#352000
0!
#354000
b101 ^
1!
#356000
0!
#358000
b110 ^
1!
#360000
0!
#362000
b111 ^
1!
#364000
0!
#366000
b0 ^
1!
#368000
0!
#370000
b1 ^
1!
#372000
0!
#374000
b10 ^
1!
#376000
0!
#378000
b11 ^
1!
#380000
0!
#382000
b100 ^
1!
#384000
0!
#386000
b101 ^
1!
#388000
0!
#390000
b110 ^
1!
#392000
0!
#394000
b111 ^
1!
#396000
0!
#398000
b0 ^
1!
#400000
0!
#402000
b1 ^
1!
#404000
0!
#406000
b10 ^
1!
#408000
0!
#410000
b11 ^
1!
#412000
0!
#414000
b100 ^
1!
#416000
0!
#418000
b101 ^
1!
#420000
0!
#422000
b110 ^
1!
#424000
0!
#426000
b111 ^
1!
#428000
0!
#430000
b0 ^
1!
#432000
0!
#434000
b1 ^
1!
#436000
0!
#438000
b10 ^
1!
#440000
0!
#442000
b11 ^
1!
#444000
0!
#446000
b100 ^
1!
#448000
0!
#450000
b101 ^
1!
#452000
0!
#454000
b110 ^
1!
#456000
0!
#458000
b111 ^
1!
#460000
0!
#462000
b0 ^
1!
#464000
0!
#466000
b1 ^
1!
#468000
0!
#470000
b10 ^
1!
#472000
0!
#474000
b11 ^
1!
#476000
0!
#478000
b100 ^
1!
#480000
0!
#482000
b101 ^
1!
#484000
0!
#486000
b110 ^
1!
#488000
0!
#490000
b111 ^
1!
#492000
0!
#494000
b0 ^
1!
#496000
0!
#498000
b1 ^
1!
#500000
0!
#502000
b10 ^
1!
#504000
0!
#506000
b11 ^
1!
#508000
0!
#510000
b100 ^
1!
#512000
0!
#514000
b101 ^
1!
#516000
0!
#518000
b110 ^
1!
#520000
0!
#522000
b111 ^
1!
#524000
0!
#526000
b0 ^
1!
#528000
0!
#530000
b1 ^
1!
#532000
0!
#534000
b10 ^
1!
#536000
0!
#538000
b11 ^
1!
#540000
0!
#542000
b100 ^
1!
#544000
0!
#546000
b101 ^
1!
#548000
0!
#550000
b110 ^
1!
#552000
0!
#554000
b111 ^
1!
#556000
0!
#558000
b0 ^
1!
#560000
0!
#562000
b1 ^
1!
#564000
0!
#566000
b10 ^
1!
#568000
0!
#570000
b11 ^
1!
#572000
0!
#574000
b100 ^
1!
#576000
0!
#578000
b101 ^
1!
#580000
0!
#582000
b110 ^
1!
#584000
0!
#586000
b111 ^
1!
#588000
0!
#590000
b0 ^
1!
#592000
0!
#594000
b1 ^
1!
#596000
0!
#598000
b10 ^
1!
#600000
0!
#602000
b11 ^
1!
#604000
0!
#606000
b100 ^
1!
#608000
0!
#610000
b101 ^
1!
#612000
0!
#614000
b110 ^
1!
#616000
0!
#618000
b111 ^
1!
#620000
0!
#622000
b0 ^
1!
#624000
0!
#626000
b1 ^
1!
#628000
0!
#630000
b10 ^
1!
#632000
0!
#634000
b11 ^
1!
#636000
0!
#638000
b100 ^
1!
#640000
0!
#642000
b101 ^
1!
#644000
0!
#646000
b110 ^
1!
#648000
0!
#650000
b111 ^
1!
#652000
0!
#654000
b0 ^
1!
#656000
0!
#658000
b1 ^
1!
#660000
0!
#662000
b10 ^
1!
#664000
0!
#666000
b11 ^
1!
#668000
0!
#670000
b100 ^
1!
#672000
0!
#674000
b101 ^
1!
#676000
0!
#678000
b110 ^
1!
#680000
0!
#682000
b111 ^
1!
#684000
0!
#686000
b0 ^
1!
#688000
0!
#690000
b1 ^
1!
#692000
0!
#694000
b10 ^
1!
#696000
0!
#698000
b11 ^
1!
#700000
0!
#702000
b100 ^
1!
#704000
0!
#706000
b101 ^
1!
#708000
0!
#710000
b110 ^
1!
#712000
0!
#714000
b111 ^
1!
#716000
0!
#718000
b0 ^
1!
#720000
0!
#722000
b1 ^
1!
#724000
0!
#726000
b10 ^
1!
#728000
0!
#730000
b11 ^
1!
#732000
0!
#734000
b100 ^
1!
#736000
0!
#738000
b101 ^
1!
#740000
0!
#742000
b110 ^
1!
#744000
0!
#746000
b111 ^
1!
#748000
0!
#750000
b0 ^
1!
#752000
0!
#754000
b1 ^
1!
#756000
0!
#758000
b10 ^
1!
#760000
0!
#762000
b11 ^
1!
#764000
0!
#766000
b100 ^
1!
#768000
0!
#770000
b101 ^
1!
#772000
0!
#774000
b110 ^
1!
#776000
0!
#778000
b111 ^
1!
#780000
0!
#782000
b0 ^
1!
#784000
0!
#786000
b1 ^
1!
#788000
0!
#790000
b10 ^
1!
#792000
0!
#794000
b11 ^
1!
#796000
0!
#798000
b100 ^
1!
#800000
0!
#802000
b101 ^
1!
#804000
0!
#806000
b110 ^
1!
#808000
0!
#810000
b111 ^
1!
#812000
0!
#814000
b0 ^
1!
#816000
0!
#818000
b1 ^
1!
#820000
0!
#822000
b10 ^
1!
#824000
0!
#826000
b11 ^
1!
#828000
0!
#830000
b100 ^
1!
#832000
0!
#834000
b101 ^
1!
#836000
0!
#838000
b110 ^
1!
#840000
0!
#842000
b111 ^
1!
#844000
0!
#846000
b0 ^
1!
#848000
0!
#850000
b1 ^
1!
#852000
0!
#854000
b10 ^
1!
#856000
0!
#858000
b11 ^
1!
#860000
0!
#862000
b100 ^
1!
#864000
0!
#866000
b101 ^
1!
#868000
0!
#870000
b110 ^
1!
#872000
0!
#874000
b111 ^
1!
#876000
0!
#878000
b0 ^
1!
#880000
0!
#882000
b1 ^
1!
#884000
0!
#886000
b10 ^
1!
#888000
0!
#890000
b11 ^
1!
#892000
0!
#894000
b100 ^
1!
#896000
0!
#898000
b101 ^
1!
#900000
0!
#902000
b110 ^
1!
#904000
0!
#906000
b111 ^
1!
#908000
0!
#910000
b0 ^
1!
#912000
0!
#914000
b1 ^
1!
#916000
0!
#918000
b10 ^
1!
#920000
0!
#922000
b11 ^
1!
#924000
0!
#926000
b100 ^
1!
#928000
0!
#930000
b101 ^
1!
#932000
0!
#934000
b110 ^
1!
#936000
0!
#938000
b111 ^
1!
#940000
0!
#942000
b0 ^
1!
#944000
0!
#946000
b1 ^
1!
#948000
0!
#950000
b10 ^
1!
#952000
0!
#954000
b11 ^
1!
#956000
0!
#958000
b100 ^
1!
#960000
0!
#962000
b101 ^
1!
#964000
0!
#966000
b110 ^
1!
#968000
0!
#970000
b111 ^
1!
#972000
0!
#974000
b0 ^
1!
#976000
0!
#978000
b1 ^
1!
#980000
0!
#982000
b10 ^
1!
#984000
0!
#986000
b11 ^
1!
#988000
0!
#990000
b100 ^
1!
#992000
0!
#994000
b101 ^
1!
#996000
0!
#998000
b110 ^
1!
#1000000
0!
#1002000
b111 ^
1!
#1004000
0!
#1006000
b0 ^
1!
#1008000
0!
#1010000
b1 ^
1!
#1012000
0!
#1014000
b10 ^
1!
#1016000
0!
#1018000
b11 ^
1!
#1020000
0!
#1022000
b100 ^
1!
#1024000
0!
#1026000
b101 ^
1!
#1028000
0!
#1030000
b110 ^
1!
#1032000
0!
#1034000
b111 ^
1!
#1036000
0!
#1038000
b0 ^
1!
#1040000
0!
#1042000
b1 ^
1!
#1044000
0!
#1046000
b10 ^
1!
#1048000
0!
#1050000
b11 ^
1!
#1052000
0!
#1054000
b100 ^
1!
#1056000
0!
#1058000
b101 ^
1!
#1060000
0!
#1062000
b110 ^
1!
#1064000
0!
#1066000
b111 ^
1!
#1068000
0!
#1070000
b0 ^
1!
#1072000
0!
#1074000
b1 ^
1!
#1076000
0!
#1078000
b10 ^
1!
#1080000
0!
#1082000
b11 ^
1!
#1084000
0!
#1086000
b100 ^
1!
#1088000
0!
#1090000
b101 ^
1!
#1092000
0!
#1094000
b110 ^
1!
#1096000
0!
#1098000
b111 ^
1!
#1100000
0!
#1102000
b0 ^
1!
#1104000
0!
#1106000
b1 ^
1!
#1108000
0!
#1110000
b10 ^
1!
#1112000
0!
#1114000
b11 ^
1!
#1116000
0!
#1118000
b100 ^
1!
#1120000
0!
#1122000
b101 ^
1!
#1124000
0!
#1126000
b110 ^
1!
#1128000
0!
#1130000
b111 ^
1!
#1132000
0!
#1134000
b0 ^
1!
#1136000
0!
#1138000
b1 ^
1!
#1140000
0!
#1142000
b10 ^
1!
#1144000
0!
#1146000
b11 ^
1!
#1148000
0!
#1150000
b100 ^
1!
#1152000
0!
#1154000
b101 ^
1!
#1156000
0!
#1158000
b110 ^
1!
#1160000
0!
#1162000
b111 ^
1!
#1164000
0!
#1166000
b0 ^
1!
#1168000
0!
#1170000
b1 ^
1!
#1172000
0!
#1174000
b10 ^
1!
#1176000
0!
#1178000
b11 ^
1!
#1180000
0!
#1182000
b100 ^
1!
#1184000
0!
#1186000
b101 ^
1!
#1188000
0!
#1190000
b110 ^
1!
#1192000
0!
#1194000
b111 ^
1!
#1196000
0!
#1198000
b0 ^
1!
#1200000
0!
#1202000
b1 ^
1!
#1204000
0!
#1206000
b10 ^
1!
#1208000
0!
#1210000
b11 ^
1!
#1212000
0!
#1214000
b100 ^
1!
#1216000
0!
#1218000
b101 ^
1!
#1220000
0!
#1222000
b110 ^
1!
#1224000
0!
#1226000
b111 ^
1!
#1228000
0!
#1230000
b0 ^
1!
#1232000
0!
#1234000
b1 ^
1!
#1236000
0!
#1238000
b10 ^
1!
#1240000
0!
#1242000
b11 ^
1!
#1244000
0!
#1246000
b100 ^
1!
#1248000
0!
#1250000
b101 ^
1!
#1252000
0!
#1254000
b110 ^
1!
#1256000
0!
#1258000
b111 ^
1!
#1260000
0!
#1262000
b0 ^
1!
#1264000
0!
#1266000
b1 ^
1!
#1268000
0!
#1270000
b10 ^
1!
#1272000
0!
#1274000
b11 ^
1!
#1276000
0!
#1278000
b100 ^
1!
#1280000
0!
#1282000
b101 ^
1!
#1284000
0!
#1286000
b110 ^
1!
#1288000
0!
#1290000
b111 ^
1!
#1292000
0!
#1294000
b0 ^
1!
#1296000
0!
#1298000
b1 ^
1!
#1300000
0!
#1302000
b10 ^
1!
#1304000
0!
#1306000
b11 ^
1!
#1308000
0!
#1310000
b100 ^
1!
#1312000
0!
